LICENSE
MANIFEST.in
README.rst
nimsp.py
setup.py
nimsp.egg-info/PKG-INFO
nimsp.egg-info/SOURCES.txt
nimsp.egg-info/dependency_links.txt
nimsp.egg-info/top_level.txt