Metadata-Version: 1.0
Name: nimsp
Version: 0.3.4
Summary: Library for interacting with the National Institute on Money in State Politics API
Home-page: http://github.com/sunlightlabs/python-nimsp
Author: Michael Stephens
Author-email: mstephens@sunlightfoundation.com
License: BSD
Platform: any
Classifier: Development Status :: 4 - Beta
Classifier: Intended Audience :: Developers
Classifier: License :: OSI Approved :: BSD License
Classifier: Natural Language :: English
Classifier: Operating System :: OS Independent
Classifier: Programming Language :: Python
Classifier: Topic :: Software Development :: Libraries :: Python Modules
